symm_learning/linalg.py
symm_learning/representation_theory.py
symm_learning/stats.py
symm_learning/utils.py
symm_learning/models/__init__.py
symm_learning/models/emlp.py
symm_learning/models/imlp.py
symm_learning/models/difussion/cond_eunet1d.py
symm_learning/models/difussion/cond_unet1d.py
symm_learning/models/time_cnn/cnn_encoder.py
symm_learning/models/time_cnn/ecnn_encoder.py
symm_learning/nn/__init__.py
symm_learning/nn/activations.py
symm_learning/nn/affine.py
symm_learning/nn/conv.py
symm_learning/nn/disentangled.py
symm_learning/nn/distributions.py
symm_learning/nn/normalization.py
symm_learning/nn/pooling.py
symm_learning-0.2.21.dist-info/METADATA
symm_learning-0.2.21.dist-info/WHEEL
symm_learning-0.2.21.dist-info/RECORD
