Metadata-Version: 2.4
Name: symm-learning
Version: 0.2.21
Summary: Torch modules and utilities of equivariant/invariant learning
Author-email: Daniel Ordoñez <daniels.ordonez@gmail.com>
Requires-Python: >=3.8
Requires-Dist: escnn
Requires-Dist: torch
Provides-Extra: dev
Requires-Dist: pre-commit; extra == 'dev'
Requires-Dist: pytest; extra == 'dev'
Requires-Dist: renku-sphinx-theme; extra == 'dev'
Requires-Dist: ruff; extra == 'dev'
Requires-Dist: sphinx-autobuild; extra == 'dev'
Provides-Extra: docs
Requires-Dist: renku-sphinx-theme; extra == 'docs'
